{
  "projects": [
    {
      "name": "Teste",
      "budget": "5000",
      "category": {
        "id": "2",
        "name": "Desenvolvimento"
      },
      "cost": 0,
      "services": [],
      "id": 1
    },
    {
      "name": "Teste2",
      "budget": "2132341",
      "category": {
        "id": "1",
        "name": "Infra"
      },
      "cost": 0,
      "services": [],
      "id": 2
    },
    {
      "name": "Teste3",
      "budget": "1231231",
      "category": {
        "id": "2",
        "name": "Desenvolvimento"
      },
      "cost": 0,
      "services": [],
      "id": 3
    },
    {
      "name": "Teste4 a",
      "budget": "1500",
      "category": {
        "id": "4",
        "name": "Planejamento"
      },
      "cost": 0,
      "services": [],
      "id": 4
    },
    {
      "name": "Teste5",
      "budget": "213",
      "category": {
        "id": "2",
        "name": "Desenvolvimento"
      },
      "cost": 0,
      "services": [],
      "id": 5
    }
  ],
  "categories": [
    {
      "id": "1",
      "name": "Infra"
    },
    {
      "id": "2",
      "name": "Desenvolvimento"
    },
    {
      "id": "3",
      "name": "Design"
    },
    {
      "id": "4",
      "name": "Planejamento"
    }
  ]
}